ghostPii/__init__.py
ghostPii/ciphertext.py
ghostPii/db_toolbox.py
ghostPii/encoding.py
ghostPii/num_theory_toolbox.py
ghostPii/polynomial.py
ghostPii/recrypt.py
ghostPii/seed_to_hash.py
ghostPii/data_structures/__init__.py
ghostPii/data_structures/norm_cipher_frame.py
ghostPii/data_structures/norm_cipher_list.py
ghostPii/data_structures/norm_cipher_num.py
ghostPii/data_structures/norm_cipher_quant.py
ghostPii/data_structures/norm_cipher_string.py
ghostPii/data_structures/paillier_num.py
ghostPii-1.0.14.dist-info/LICENSE
ghostPii-1.0.14.dist-info/METADATA
ghostPii-1.0.14.dist-info/WHEEL
ghostPii-1.0.14.dist-info/top_level.txt
ghostPii-1.0.14.dist-info/RECORD
