Metadata-Version: 2.1
Name: ghostPii
Version: 1.0.14
Summary: A private computation package
Home-page: https://github.com/capnion/ghostpii_client
Author: Capnion Inc.
Author-email: acmueller@capnion.com
Project-URL: full_repo, https://github.com/capnion/ghostpii_client
Classifier: Programming Language :: Python :: 3
Classifier: License :: OSI Approved :: MIT License
Classifier: Operating System :: OS Independent
Requires-Python: >=3.6
License-File: LICENSE
Requires-Dist: numpy
Requires-Dist: pandas
Requires-Dist: SQLAlchemy
Requires-Dist: scipy
Requires-Dist: sympy
Requires-Dist: IPython
